syscord/__init__.py
syscord-0.1.0.dist-info/METADATA
syscord-0.1.0.dist-info/WHEEL
syscord-0.1.0.dist-info/RECORD
