Metadata-Version: 2.1
Name: syscord
Version: 0.1.0
Summary: the simple python discord system api
Author: Andrew
Author-email: contact@andrew.us
Requires-Python: >=3.11,<4.0
Classifier: Programming Language :: Python :: 3
Classifier: Programming Language :: Python :: 3.11
